[
  {
    "id": "local-custom-1",
    "mal_id": 38000,
    "title": " Demon Slayer",
    "title_japanese": "鬼滅の刃",
    "type": "TV",
    "episodes": 26,
    "status": "Finished Airing",
    "score": 8.6,
    "synopsis": "Teenage demon slayer Tanjiro Kamado fights demons and seeks a cure for his sister's transformation...",
    "genres": ["Action", "Fantasy"],
    "image": "https://cdn.myanimelist.net/images/anime/1286/99889.jpg",
    "year": 2019,
    "featured": true,
    "embed_providers": {
      "hianime": "demon-slayer-kimetsu-no-yaiba-3498",
      "gogoanime": "kimetsu-no-yaiba"
    },
    "published_at": "2025-01-01"
  },
  {
    "id": "local-custom-2",
    "mal_id": 51160,
    "title": "Chainsaw Man",
    "title_japanese": "チェインソーマン",
    "type": "TV",
    "episodes": 12,
    "status": "Finished Airing",
    "score": 8.3,
    "synopsis": "Denji is a young man trapped in poverty, until he merges with his pet chainsaw devil...",
    "genres": ["Action", "Horror"],
    "image": "https://cdn.myanimelist.net/images/anime/180c/141358.jpg",
    "year": 2022,
    "featured": false,
    "embed_providers": {
      "hianime": "chainsaw-man-9067",
      "gogoanime": "chainsaw-man"
    },
    "published_at": "2025-02-01"
  }
]
